orbitsim/Engine.py
orbitsim/Environment.py
orbitsim/Orbit.py
orbitsim/Spacecraft.py
orbitsim/Util.py
orbitsim/__init__.py
orbitsim/orbitsim.py
orbitsim/util.py
tests/__init__.py
tests/context.py
orbitsim-0.2.0.dist-info/LICENSE
orbitsim-0.2.0.dist-info/METADATA
orbitsim-0.2.0.dist-info/WHEEL
orbitsim-0.2.0.dist-info/top_level.txt
orbitsim-0.2.0.dist-info/RECORD
