Metadata-Version: 2.1
Name: orbitsim
Version: 0.2.0
Summary: 3D orbit simulation visualisation tool
Home-page: https://github.com/alexander-minchin/orbitsim
Author: Alexander Minchin
Author-email: alexander.w.minchin@gmail.com
License: Copyright (c) 2021, Alexander Minchin        
Platform: UNKNOWN
Classifier: Programming Language :: Python :: 3
Classifier: License :: OSI Approved :: MIT License
Classifier: Operating System :: OS Independent
Requires-Python: >=3.6
Requires-Dist: numpy (>=1.0)
Requires-Dist: scipy (>=1.0)
Requires-Dist: pyatmos
Requires-Dist: mayavi
Requires-Dist: kepler
